{
    "basic_info": {
      "name": "Soowhan Park",
      "titles": ["Software Engineer"],
      "social": [
        {
          "name": "github",
          "url": "https://github.com",
          "class": "fab fa-github"
        },
        {
          "name": "linkedin",
          "url": "https://www.linkedin.com",
          "class": "fab fa-linkedin-in"
        }
      ],
      "image": "profile.jpg"
    },
    "skills": {
      "icons": [
        {
          "name": "Python",
          "class": "devicon-python-plain",
          "level": "65"
        },
        {
          "name": "HTML 5",
          "class": "devicon-html5-plain",
          "level": "95"
        },
        {
          "name": "TypeScript",
          "class": "devicon-typescript-plain",
          "level": "90"
        },
        {
          "name": "JavaScript",
          "class": "devicon-javascript-plain",
          "level": "70"
        },
        {
          "name": "Docker",
          "class": "devicon-docker-plain-wordmark",
          "level": "85"
        },
        {
          "name": "MySql",
          "class": "devicon-mysql-plain",
          "level": "60"
        }
      ]
    }
  }